{"stats":{"minecraft:custom":{"minecraft:time_since_rest":7560,"minecraft:open_chest":4,"minecraft:crouch_one_cm":8,"minecraft:play_time":10177,"minecraft:sprint_one_cm":38309,"minecraft:walk_one_cm":71744,"minecraft:damage_taken":568,"minecraft:deaths":1,"minecraft:sneak_time":22,"minecraft:mob_kills":1,"minecraft:interact_with_lectern":1,"minecraft:damage_dealt_resisted":3351,"minecraft:jump":181,"minecraft:damage_dealt":65,"minecraft:time_since_death":7522,"minecraft:total_world_time":10177,"minecraft:climb_one_cm":1171,"minecraft:damage_resisted":81,"minecraft:interact_with_crafting_table":1,"minecraft:fall_one_cm":8174,"minecraft:fly_one_cm":53201},"minecraft:mined":{"minecraft:grass":2,"minecraft:spruce_leaves":8},"minecraft:killed":{"kimetsunoyaiba:yorichi_0":1},"minecraft:used":{"kimetsunoyaiba:nichirinswordmoon":9},"minecraft:picked_up":{"kimetsunoyaiba:blood_of_muzan":1}},"DataVersion":3465}